{
  "arch": "x86_64",
  "build": "py313h7040dfc_1",
  "build_number": 1,
  "channel": "https://repo.anaconda.com/pkgs/main/linux-64/",
  "constrains": [
    "ipywidgets >=6"
  ],
  "depends": [
    "python >=3.13,<3.14.0a0",
    "python_abi 3.13.* *_cp313"
  ],
  "fn": "tqdm-4.67.1-py313h7040dfc_1.conda",
  "license": "MPL-2.0 AND MIT",
  "license_family": "MOZILLA",
  "md5": "45ba169c5e50d8b0e0c23b495dcc2cd6",
  "name": "tqdm",
  "platform": "linux",
  "sha256": "169191d6b946a50d4db20294ea12f0fa1ae4923f40a5ff52bfa82da767c506fb",
  "size": 160288,
  "subdir": "linux-64",
  "timestamp": 1762863368000,
  "url": "https://repo.anaconda.com/pkgs/main/linux-64/tqdm-4.67.1-py313h7040dfc_1.conda",
  "version": "4.67.1"
}