{
  "arch": "x86_64",
  "build": "hb25bd0a_0",
  "build_number": 0,
  "channel": "https://repo.anaconda.com/pkgs/main/linux-64/",
  "constrains": [],
  "depends": [
    "__glibc >=2.17,<3.0.a0",
    "libgcc-ng >=11.2.0",
    "libzlib 1.3.1 hb25bd0a_0"
  ],
  "fn": "zlib-1.3.1-hb25bd0a_0.conda",
  "license": "Zlib",
  "license_family": "OTHER",
  "md5": "9f3a877e5e0fa0fb39253a59ff824861",
  "name": "zlib",
  "platform": "linux",
  "sha256": "cf30f83189a30b12a9239f132ea0ce676fa822a52045adb0f9ff9b3b4d79ead6",
  "size": 98150,
  "subdir": "linux-64",
  "timestamp": 1756475939000,
  "url": "https://repo.anaconda.com/pkgs/main/linux-64/zlib-1.3.1-hb25bd0a_0.conda",
  "version": "1.3.1"
}